analytics/__init__.py
analytics/reporter.py
cli/__init__.py
cli/app.py
cli/audio.py
cli/cli_analytics.py
cli/cli_utils.py
cli/error_handlers.py
cli/files.py
cli/update.py
cli/video.py
cli/worker.py
core/__init__.py
core/analytics_dashboard.py
core/base.py
core/base_service.py
core/config.py
core/database_service.py
core/decorators.py
core/error_handler.py
core/file_tracker.py
core/interactive_cli.py
core/interfaces.py
core/job_queue.py
core/logger.py
core/package_updater.py
core/progress.py
core/service_factory.py
core/streaming.py
core/worker.py
database/__init__.py
database/connection.py
database/metadata.py
database/models.py
database/repository.py
database/transcription_storage.py
modules/__init__.py
modules/audio/__init__.py
modules/audio/converter.py
modules/video/__init__.py
modules/video/converter.py
modules/video/fallback_extractor.py
modules/video/youtube_api.py
modules/video/services/__init__.py
modules/video/services/audio_extraction_service.py
modules/video/services/download_service.py
modules/video/services/metadata_service.py
modules/video/services/playlist_service.py
modules/video/services/transcription_service.py
spatelier/__init__.py
spatelier-0.4.0.dist-info/licenses/LICENSE
utils/__init__.py
utils/cookie_manager.py
utils/format_selector.py
utils/helpers.py
utils/ytdlp_auth_handler.py
spatelier-0.4.0.dist-info/METADATA
spatelier-0.4.0.dist-info/WHEEL
spatelier-0.4.0.dist-info/entry_points.txt
spatelier-0.4.0.dist-info/top_level.txt
spatelier-0.4.0.dist-info/RECORD
