Metadata-Version: 2.4
Name: spatelier
Version: 0.4.0
Summary: Personal tool library for video and music file handling
Author-email: Galen Spikes <galenspikes@gmail.com>
License: MIT
Project-URL: Homepage, https://github.com/galenspikes/spatelier
Project-URL: Documentation, https://github.com/galenspikes/spatelier#readme
Project-URL: Repository, https://github.com/galenspikes/spatelier
Project-URL: Issues, https://github.com/galenspikes/spatelier/issues
Project-URL: Changelog, https://github.com/galenspikes/spatelier/blob/main/CHANGELOG.md
Keywords: video,audio,media,youtube,download,transcription,processing,cli,tool
Classifier: Development Status :: 3 - Alpha
Classifier: Intended Audience :: Developers
Classifier: License :: OSI Approved :: MIT License
Classifier: Programming Language :: Python :: 3
Classifier: Programming Language :: Python :: 3.10
Classifier: Programming Language :: Python :: 3.11
Classifier: Programming Language :: Python :: 3.12
Classifier: Topic :: Multimedia :: Video
Classifier: Topic :: Multimedia :: Sound/Audio
Classifier: Topic :: Utilities
Requires-Python: >=3.10
License-File: LICENSE
Requires-Dist: typer[all]>=0.9.0
Requires-Dist: rich>=13.0.0
Requires-Dist: click>=8.0.0
Requires-Dist: pydantic>=2.0.0
Requires-Dist: pyyaml>=6.0.0
Requires-Dist: loguru>=0.7.0
Requires-Dist: yt-dlp>=2023.12.30
Requires-Dist: ffmpeg-python>=0.2.0
Requires-Dist: mutagen>=1.47.0
Requires-Dist: pillow>=10.0.0
Requires-Dist: faster-whisper>=0.9.0
Requires-Dist: sqlalchemy>=2.0.0
Requires-Dist: alembic>=1.12.0
Provides-Extra: youtube-api
Requires-Dist: google-api-python-client>=2.0.0; extra == "youtube-api"
Requires-Dist: google-auth-httplib2>=0.1.0; extra == "youtube-api"
Requires-Dist: google-auth-oauthlib>=1.0.0; extra == "youtube-api"
Provides-Extra: analytics
Requires-Dist: pandas>=2.0.0; extra == "analytics"
Requires-Dist: matplotlib>=3.7.0; extra == "analytics"
Requires-Dist: seaborn>=0.12.0; extra == "analytics"
Requires-Dist: plotly>=5.15.0; extra == "analytics"
Provides-Extra: mongodb
Requires-Dist: pymongo>=4.5.0; extra == "mongodb"
Requires-Dist: motor>=3.3.0; extra == "mongodb"
Provides-Extra: web
Requires-Dist: beautifulsoup4>=4.12.0; extra == "web"
Requires-Dist: playwright>=1.40.0; extra == "web"
Requires-Dist: requests>=2.31.0; extra == "web"
Provides-Extra: all
Requires-Dist: google-api-python-client>=2.0.0; extra == "all"
Requires-Dist: google-auth-httplib2>=0.1.0; extra == "all"
Requires-Dist: google-auth-oauthlib>=1.0.0; extra == "all"
Requires-Dist: pandas>=2.0.0; extra == "all"
Requires-Dist: matplotlib>=3.7.0; extra == "all"
Requires-Dist: seaborn>=0.12.0; extra == "all"
Requires-Dist: plotly>=5.15.0; extra == "all"
Requires-Dist: pymongo>=4.5.0; extra == "all"
Requires-Dist: motor>=3.3.0; extra == "all"
Requires-Dist: beautifulsoup4>=4.12.0; extra == "all"
Requires-Dist: playwright>=1.40.0; extra == "all"
Requires-Dist: requests>=2.31.0; extra == "all"
Provides-Extra: dev
Requires-Dist: pytest>=7.0.0; extra == "dev"
Requires-Dist: pytest-asyncio>=0.21.0; extra == "dev"
Requires-Dist: pytest-cov>=4.0.0; extra == "dev"
Requires-Dist: black>=23.0.0; extra == "dev"
Requires-Dist: isort>=5.12.0; extra == "dev"
Requires-Dist: flake8>=6.0.0; extra == "dev"
Requires-Dist: mypy>=1.0.0; extra == "dev"
Requires-Dist: pre-commit>=3.0.0; extra == "dev"
Requires-Dist: psutil>=7.2.1; extra == "dev"
Requires-Dist: alembic>=1.18.1; extra == "dev"
Requires-Dist: pandas>=2.0.0; extra == "dev"
Requires-Dist: matplotlib>=3.7.0; extra == "dev"
Requires-Dist: seaborn>=0.12.0; extra == "dev"
Requires-Dist: plotly>=5.15.0; extra == "dev"
Dynamic: license-file
